jmaddress/__init__.py
jmaddress/addressResource.py
jmaddress/juggleStr.py
jmaddress-0.6.dist-info/LICENSE
jmaddress-0.6.dist-info/METADATA
jmaddress-0.6.dist-info/WHEEL
jmaddress-0.6.dist-info/top_level.txt
jmaddress-0.6.dist-info/RECORD
