Metadata-Version: 2.1
Name: jmaddress
Version: 0.6
Summary: 返回一个tuple
Home-page: UNKNOWN
Author: jacky huang
Author-email: UNKNOWN
License: UNKNOWN
Platform: UNKNOWN
